{
  "aspectWidth": 4,
  "aspectHeight": 3,
  "enableKeyboardZoom": true,
  "enableKeyboardRotation": true,
  "enableKeyboardNavigation": true,
  "enableMouseTranslation": true,
  "enableMouseZoom": true,
  "enableMouseRotation": true,
  "enableMouseNavigation": true,
  "frames": [
    {
      "frameId": "frame6406",
      "title": "New frame",
      "timeoutMs": 0,
      "timeoutEnable": false,
      "transitionDurationMs": 0,
      "showInFrameList": true,
      "showFrameNumber": true,
      "layerProperties": {
        "layer1": {
          "link": false,
          "referenceElementId": "text4705",
          "outlineElementId": "text4705",
          "outlineElementAuto": false,
          "transitionTimingFunction": "linear",
          "transitionRelativeZoom": 0,
          "transitionPathId": ""
        },
        "__sozi_auto__": {
          "link": false,
          "referenceElementId": "",
          "outlineElementId": "text4705",
          "outlineElementAuto": false,
          "transitionTimingFunction": "linear",
          "transitionRelativeZoom": 0,
          "transitionPathId": ""
        }
      },
      "cameraStates": {
        "layer1": {
          "cx": 1386.0694668758765,
          "cy": 1236.8902331970007,
          "width": 46.78445529921278,
          "height": 12.701630355227053,
          "opacity": 1,
          "angle": 0,
          "clipped": false,
          "clipXOffset": 0,
          "clipYOffset": 0,
          "clipWidthFactor": 0.9999999999999998,
          "clipHeightFactor": 0.9999999999999997
        },
        "__sozi_auto__": {
          "cx": 1471.6706051784538,
          "cy": 1220.8958250263117,
          "width": 1.3323529411764705,
          "height": 1,
          "opacity": 1,
          "angle": 0,
          "clipped": false,
          "clipXOffset": 0,
          "clipYOffset": 0,
          "clipWidthFactor": 0.6768393620286869,
          "clipHeightFactor": 1
        }
      },
      "cameraOffsets": {
        "layer1": {
          "deltaX": -0.4349276553734853,
          "deltaY": -1.4544933654992747,
          "widthFactor": 5.04535660918473,
          "heightFactor": 2.534296256709861,
          "deltaAngle": 0
        }
      }
    },
    {
      "frameId": "frame9463",
      "title": "New frame",
      "timeoutMs": 0,
      "timeoutEnable": false,
      "transitionDurationMs": 1400,
      "showInFrameList": true,
      "showFrameNumber": true,
      "layerProperties": {
        "layer1": {
          "link": false,
          "referenceElementId": "image18-3",
          "outlineElementId": "image18-3",
          "outlineElementAuto": true,
          "transitionTimingFunction": "linear",
          "transitionRelativeZoom": 0,
          "transitionPathId": ""
        },
        "__sozi_auto__": {
          "link": false,
          "referenceElementId": "path4591",
          "outlineElementId": "image18-3",
          "outlineElementAuto": true,
          "transitionTimingFunction": "linear",
          "transitionRelativeZoom": 0,
          "transitionPathId": ""
        }
      },
      "cameraStates": {
        "layer1": {
          "cx": 684.3528521564784,
          "cy": 1147.9879365386219,
          "width": 309.4300752408109,
          "height": 232.07255643060802,
          "opacity": 1,
          "angle": 0,
          "clipped": false,
          "clipXOffset": 0,
          "clipYOffset": 0,
          "clipWidthFactor": 0.999302519797127,
          "clipHeightFactor": 0.9999999999999936
        },
        "__sozi_auto__": {
          "cx": 1327.6279392185538,
          "cy": 1173.5629888099934,
          "width": 168.26564320745427,
          "height": 126.19933294416957,
          "opacity": 1,
          "angle": 0,
          "clipped": false,
          "clipXOffset": 0,
          "clipYOffset": 0,
          "clipWidthFactor": 0.9866024653186252,
          "clipHeightFactor": 0.9999999999999936
        }
      },
      "cameraOffsets": {
        "layer1": {
          "deltaX": -237.30455751149032,
          "deltaY": 515.1045136870594,
          "widthFactor": 0.16786614241860204,
          "heightFactor": 0.18334543417940985,
          "deltaAngle": 0
        }
      }
    },
    {
      "frameId": "frame2240",
      "title": "New frame",
      "timeoutMs": 0,
      "timeoutEnable": false,
      "transitionDurationMs": 1000,
      "showInFrameList": true,
      "showFrameNumber": true,
      "layerProperties": {
        "layer1": {
          "link": false,
          "referenceElementId": "image5416",
          "outlineElementId": "image5416",
          "outlineElementAuto": true,
          "transitionTimingFunction": "linear",
          "transitionRelativeZoom": 0,
          "transitionPathId": ""
        },
        "__sozi_auto__": {
          "link": false,
          "referenceElementId": "path4591",
          "outlineElementId": "image5416",
          "outlineElementAuto": true,
          "transitionTimingFunction": "linear",
          "transitionRelativeZoom": 0,
          "transitionPathId": ""
        }
      },
      "cameraStates": {
        "layer1": {
          "cx": 1447.5636021763153,
          "cy": 1172.485010719658,
          "width": 117.96101962711273,
          "height": 82.83577986772099,
          "opacity": 1,
          "angle": 0,
          "clipped": false,
          "clipXOffset": 0,
          "clipYOffset": 0,
          "clipWidthFactor": 0.9978864254999952,
          "clipHeightFactor": 0.9978421288014189
        },
        "__sozi_auto__": {
          "cx": 1679.7317493814255,
          "cy": 1186.6198817921857,
          "width": 5.023219206340632,
          "height": 3.7702112974093382,
          "opacity": 1,
          "angle": 0,
          "clipped": false,
          "clipXOffset": 0,
          "clipYOffset": 0,
          "clipWidthFactor": 0.9852035831710473,
          "clipHeightFactor": 0.9978421288014194
        }
      },
      "cameraOffsets": {
        "layer1": {
          "deltaX": 0.06433459819027121,
          "deltaY": -0.3736318584669789,
          "widthFactor": 1.7295662191391785,
          "heightFactor": 1.748723665986341,
          "deltaAngle": 0
        }
      }
    },
    {
      "frameId": "frame9591",
      "title": "New frame",
      "timeoutMs": 0,
      "timeoutEnable": false,
      "transitionDurationMs": 1000,
      "showInFrameList": true,
      "showFrameNumber": true,
      "layerProperties": {
        "layer1": {
          "link": false,
          "referenceElementId": "image5449",
          "outlineElementId": "image5449",
          "outlineElementAuto": true,
          "transitionTimingFunction": "linear",
          "transitionRelativeZoom": 0,
          "transitionPathId": ""
        },
        "__sozi_auto__": {
          "link": false,
          "referenceElementId": "path4591",
          "outlineElementId": "image5449",
          "outlineElementAuto": true,
          "transitionTimingFunction": "linear",
          "transitionRelativeZoom": 0,
          "transitionPathId": ""
        }
      },
      "cameraStates": {
        "layer1": {
          "cx": 1072.5032573715853,
          "cy": 656.4047774547715,
          "width": 463.86526135057,
          "height": 348.44338880793987,
          "opacity": 1,
          "angle": 0,
          "clipped": false,
          "clipXOffset": 0,
          "clipYOffset": 0,
          "clipWidthFactor": 0.8811790712075701,
          "clipHeightFactor": 0.9984375
        },
        "__sozi_auto__": {
          "cx": 1456.0479573385721,
          "cy": 582.4700397406408,
          "width": 408.75314141513854,
          "height": 307.0446132695876,
          "opacity": 1,
          "angle": 0,
          "clipped": false,
          "clipXOffset": 0,
          "clipYOffset": 0,
          "clipWidthFactor": 1,
          "clipHeightFactor": 0.998438295420744
        }
      },
      "cameraOffsets": {}
    },
    {
      "frameId": "frame9683",
      "title": "New frame",
      "timeoutMs": 0,
      "timeoutEnable": false,
      "transitionDurationMs": 1000,
      "showInFrameList": true,
      "showFrameNumber": true,
      "layerProperties": {
        "layer1": {
          "link": false,
          "referenceElementId": "path1063",
          "outlineElementId": "path1063",
          "outlineElementAuto": true,
          "transitionTimingFunction": "linear",
          "transitionRelativeZoom": 0,
          "transitionPathId": ""
        },
        "__sozi_auto__": {
          "link": false,
          "referenceElementId": "path4591",
          "outlineElementId": "path1063",
          "outlineElementAuto": true,
          "transitionTimingFunction": "linear",
          "transitionRelativeZoom": 0,
          "transitionPathId": ""
        }
      },
      "cameraStates": {
        "layer1": {
          "cx": 1271.8001122450016,
          "cy": 1052.422992762466,
          "width": 9.80212010650982,
          "height": 7.356999638440039,
          "opacity": 1,
          "angle": -0.2008196645791429,
          "clipped": false,
          "clipXOffset": 0,
          "clipYOffset": 0,
          "clipWidthFactor": 0.9985829173157551,
          "clipHeightFactor": 0.9978421288014265
        },
        "__sozi_auto__": {
          "cx": 1424.8574346597022,
          "cy": 1054.8222334893683,
          "width": 8.67856322694584,
          "height": 6.513711914263986,
          "opacity": 1,
          "angle": 0,
          "clipped": false,
          "clipXOffset": 0,
          "clipYOffset": 0,
          "clipWidthFactor": 0.9985821217797953,
          "clipHeightFactor": 0.9978421288014265
        }
      },
      "cameraOffsets": {}
    },
    {
      "frameId": "frame4952",
      "title": "New frame",
      "timeoutMs": 0,
      "timeoutEnable": false,
      "transitionDurationMs": 1000,
      "showInFrameList": true,
      "showFrameNumber": true,
      "layerProperties": {
        "layer1": {
          "link": false,
          "referenceElementId": "text5362",
          "outlineElementId": "text5362",
          "outlineElementAuto": true,
          "transitionTimingFunction": "linear",
          "transitionRelativeZoom": 0,
          "transitionPathId": ""
        },
        "__sozi_auto__": {
          "link": false,
          "referenceElementId": "path4591",
          "outlineElementId": "text5362",
          "outlineElementAuto": true,
          "transitionTimingFunction": "linear",
          "transitionRelativeZoom": 0,
          "transitionPathId": ""
        }
      },
      "cameraStates": {
        "layer1": {
          "cx": 241.5628334390958,
          "cy": 470.79504789899397,
          "width": 427.54534479155274,
          "height": 329.2953764121156,
          "opacity": 1,
          "angle": 0,
          "clipped": false,
          "clipXOffset": 0,
          "clipYOffset": 0,
          "clipWidthFactor": 0.9994036970781102,
          "clipHeightFactor": 0.9999999999999952
        },
        "__sozi_auto__": {
          "cx": 396.8929853594709,
          "cy": 472.35290628022744,
          "width": 429.44722104011703,
          "height": 321.8933553055618,
          "opacity": 1,
          "angle": 0,
          "clipped": false,
          "clipXOffset": 0,
          "clipYOffset": 0,
          "clipWidthFactor": 0.9994029008882626,
          "clipHeightFactor": 0.9999999999999946
        }
      },
      "cameraOffsets": {
        "layer1": {
          "deltaX": -2.9140647542635634,
          "deltaY": -16.181362013115404,
          "widthFactor": 15.134348037157837,
          "heightFactor": 5.807358352795352,
          "deltaAngle": 0
        }
      }
    },
    {
      "frameId": "frame5401",
      "title": "New frame",
      "timeoutMs": 0,
      "timeoutEnable": false,
      "transitionDurationMs": 2000,
      "showInFrameList": true,
      "showFrameNumber": true,
      "layerProperties": {
        "layer1": {
          "link": false,
          "referenceElementId": "text5366",
          "outlineElementId": "text5366",
          "outlineElementAuto": true,
          "transitionTimingFunction": "linear",
          "transitionRelativeZoom": 0,
          "transitionPathId": ""
        },
        "__sozi_auto__": {
          "link": false,
          "referenceElementId": "path4591",
          "outlineElementId": "text5366",
          "outlineElementAuto": true,
          "transitionTimingFunction": "linear",
          "transitionRelativeZoom": 0,
          "transitionPathId": ""
        }
      },
      "cameraStates": {
        "layer1": {
          "cx": 1152.43885714071,
          "cy": 1109.213782486011,
          "width": 59.66290438896918,
          "height": 8.373301658746861,
          "opacity": 1,
          "angle": -0.034586284309625626,
          "clipped": false,
          "clipXOffset": 0,
          "clipYOffset": 0,
          "clipWidthFactor": 0.9999999999999969,
          "clipHeightFactor": 0.9999999999999971
        },
        "__sozi_auto__": {
          "cx": 1301.7825452860425,
          "cy": 1102.431239389869,
          "width": 9.105791026978396,
          "height": 6.834368541219988,
          "opacity": 1,
          "angle": 0,
          "clipped": false,
          "clipXOffset": 0,
          "clipYOffset": 0,
          "clipWidthFactor": 0.9999999999999947,
          "clipHeightFactor": 0.9999999999999958
        }
      },
      "cameraOffsets": {}
    },
    {
      "frameId": "frame9677",
      "title": "New frame",
      "timeoutMs": 0,
      "timeoutEnable": false,
      "transitionDurationMs": 2000,
      "showInFrameList": true,
      "showFrameNumber": true,
      "layerProperties": {
        "layer1": {
          "link": false,
          "referenceElementId": "text5370",
          "outlineElementId": "text5370",
          "outlineElementAuto": true,
          "transitionTimingFunction": "easeInOut",
          "transitionRelativeZoom": 0,
          "transitionPathId": ""
        },
        "__sozi_auto__": {
          "link": false,
          "referenceElementId": "path4591",
          "outlineElementId": "text5370",
          "outlineElementAuto": true,
          "transitionTimingFunction": "easeInOut",
          "transitionRelativeZoom": 0,
          "transitionPathId": ""
        }
      },
      "cameraStates": {
        "layer1": {
          "cx": 175.8295400275597,
          "cy": 166.89685822033027,
          "width": 344.0582733439354,
          "height": 252.93061061467435,
          "opacity": 1,
          "angle": 0,
          "clipped": false,
          "clipXOffset": 0,
          "clipYOffset": 0,
          "clipWidthFactor": 1,
          "clipHeightFactor": 1
        },
        "__sozi_auto__": {
          "cx": 330.7709542121945,
          "cy": 168.41501705941732,
          "width": 334.1813452877249,
          "height": 250.82043575679134,
          "opacity": 1,
          "angle": 0,
          "clipped": false,
          "clipXOffset": 0,
          "clipYOffset": 0,
          "clipWidthFactor": 1,
          "clipHeightFactor": 1
        }
      },
      "cameraOffsets": {
        "layer1": {
          "deltaX": 13.665141834200313,
          "deltaY": 21.170448308220898,
          "widthFactor": 12.17905356071505,
          "heightFactor": 4.460611352138969,
          "deltaAngle": 0
        }
      }
    },
    {
      "frameId": "frame5152",
      "title": "New frame",
      "timeoutMs": 0,
      "timeoutEnable": false,
      "transitionDurationMs": 2000,
      "showInFrameList": true,
      "showFrameNumber": true,
      "layerProperties": {
        "layer1": {
          "link": false,
          "referenceElementId": "image1287",
          "outlineElementId": "image18-3",
          "outlineElementAuto": false,
          "transitionTimingFunction": "ease",
          "transitionRelativeZoom": 0,
          "transitionPathId": ""
        },
        "__sozi_auto__": {
          "link": false,
          "referenceElementId": "path4591",
          "outlineElementId": "image18-3",
          "outlineElementAuto": false,
          "transitionTimingFunction": "ease",
          "transitionRelativeZoom": 0,
          "transitionPathId": ""
        }
      },
      "cameraStates": {
        "layer1": {
          "cx": 1667.933828083942,
          "cy": 1131.1209855067175,
          "width": 351.6932461353458,
          "height": 263.9640444885852,
          "opacity": 1,
          "angle": 0,
          "clipped": true,
          "clipXOffset": 0,
          "clipYOffset": 0,
          "clipWidthFactor": 0.9999999999999996,
          "clipHeightFactor": 0.9999999999999998
        },
        "__sozi_auto__": {
          "cx": 1818.1502655941022,
          "cy": 1127.346479723093,
          "width": 336.76191121867197,
          "height": 252.75728435838516,
          "opacity": 1,
          "angle": 0,
          "clipped": true,
          "clipXOffset": 0,
          "clipYOffset": 0,
          "clipWidthFactor": 0.9999999999999998,
          "clipHeightFactor": 0.9999999999999998
        }
      },
      "cameraOffsets": {}
    },
    {
      "frameId": "frame8073",
      "title": "New frame",
      "timeoutMs": 0,
      "timeoutEnable": false,
      "transitionDurationMs": 2000,
      "showInFrameList": true,
      "showFrameNumber": true,
      "layerProperties": {
        "layer1": {
          "link": false,
          "referenceElementId": "path3715-6",
          "outlineElementId": "image18-3",
          "outlineElementAuto": false,
          "transitionTimingFunction": "ease",
          "transitionRelativeZoom": 0,
          "transitionPathId": ""
        },
        "__sozi_auto__": {
          "link": false,
          "referenceElementId": "path4591",
          "outlineElementId": "image18-3",
          "outlineElementAuto": false,
          "transitionTimingFunction": "ease",
          "transitionRelativeZoom": 0,
          "transitionPathId": ""
        }
      },
      "cameraStates": {
        "layer1": {
          "cx": 1641.6828411291806,
          "cy": 721.0896367974135,
          "width": 356.8705632721993,
          "height": 267.4933202344393,
          "opacity": 1,
          "angle": 0,
          "clipped": false,
          "clipXOffset": 0,
          "clipYOffset": 0,
          "clipWidthFactor": 1,
          "clipHeightFactor": 1
        },
        "__sozi_auto__": {
          "cx": 1837.8366964192628,
          "cy": 720.5004495600978,
          "width": 353.307291542205,
          "height": 264.8224600289515,
          "opacity": 1,
          "angle": 0,
          "clipped": false,
          "clipXOffset": 0,
          "clipYOffset": 0,
          "clipWidthFactor": 1,
          "clipHeightFactor": 1
        }
      },
      "cameraOffsets": {
        "layer1": {
          "deltaX": -5.982930355194412,
          "deltaY": -40.205468183055245,
          "widthFactor": 2.1209370663216705,
          "heightFactor": 3.427115836921186,
          "deltaAngle": 0
        }
      }
    },
    {
      "frameId": "frame3114",
      "title": "New frame",
      "timeoutMs": 0,
      "timeoutEnable": false,
      "transitionDurationMs": 2000,
      "showInFrameList": true,
      "showFrameNumber": true,
      "layerProperties": {
        "layer1": {
          "link": false,
          "referenceElementId": "image4697",
          "outlineElementId": "image18-3",
          "outlineElementAuto": false,
          "transitionTimingFunction": "ease",
          "transitionRelativeZoom": 0,
          "transitionPathId": ""
        },
        "__sozi_auto__": {
          "link": false,
          "referenceElementId": "path4591",
          "outlineElementId": "image18-3",
          "outlineElementAuto": false,
          "transitionTimingFunction": "ease",
          "transitionRelativeZoom": 0,
          "transitionPathId": ""
        }
      },
      "cameraStates": {
        "layer1": {
          "cx": 1020.7002662191908,
          "cy": 1122.8139882432035,
          "width": 9.94629554358954,
          "height": 7.465259684164089,
          "opacity": 1,
          "angle": -0.034586284309625626,
          "clipped": false,
          "clipXOffset": 0,
          "clipYOffset": 0,
          "clipWidthFactor": 1,
          "clipHeightFactor": 1
        },
        "__sozi_auto__": {
          "cx": 1300.0541423590705,
          "cy": 1054.683340699333,
          "width": 77.97593666365435,
          "height": 58.525368943544585,
          "opacity": 1,
          "angle": 0,
          "clipped": false,
          "clipXOffset": 0,
          "clipYOffset": 0,
          "clipWidthFactor": 1,
          "clipHeightFactor": 1
        }
      },
      "cameraOffsets": {}
    },
    {
      "frameId": "frame5929",
      "title": "New frame",
      "timeoutMs": 0,
      "timeoutEnable": false,
      "transitionDurationMs": 2000,
      "showInFrameList": true,
      "showFrameNumber": true,
      "layerProperties": {
        "layer1": {
          "link": false,
          "referenceElementId": "text5342",
          "outlineElementId": "image18-3",
          "outlineElementAuto": false,
          "transitionTimingFunction": "ease",
          "transitionRelativeZoom": 0,
          "transitionPathId": ""
        },
        "__sozi_auto__": {
          "link": false,
          "referenceElementId": "path4591",
          "outlineElementId": "image18-3",
          "outlineElementAuto": false,
          "transitionTimingFunction": "ease",
          "transitionRelativeZoom": 0,
          "transitionPathId": ""
        }
      },
      "cameraStates": {
        "layer1": {
          "cx": 1604.5974116419054,
          "cy": 390.72437990646023,
          "width": 432.61585058561576,
          "height": 345.05391799317584,
          "opacity": 1,
          "angle": 0,
          "clipped": false,
          "clipXOffset": 0,
          "clipYOffset": 0,
          "clipWidthFactor": 0.9999934495385177,
          "clipHeightFactor": 0.9999999999999976
        },
        "__sozi_auto__": {
          "cx": 1838.313163995746,
          "cy": 371.2696973413275,
          "width": 133.4899169871069,
          "height": 100.19110767244227,
          "opacity": 1,
          "angle": 0,
          "clipped": false,
          "clipXOffset": 0,
          "clipYOffset": 0,
          "clipWidthFactor": 0.999993449538519,
          "clipHeightFactor": 0.9999999999999993
        }
      },
      "cameraOffsets": {
        "layer1": {
          "deltaX": 6.37792922003041,
          "deltaY": 4.6652368400539785,
          "widthFactor": 7.670914038666952,
          "heightFactor": 6.087420547360683,
          "deltaAngle": 0
        }
      }
    },
    {
      "frameId": "frame5688",
      "title": "New frame",
      "timeoutMs": 0,
      "timeoutEnable": false,
      "transitionDurationMs": 2000,
      "showInFrameList": true,
      "showFrameNumber": true,
      "layerProperties": {
        "layer1": {
          "link": false,
          "referenceElementId": "image18-3",
          "outlineElementId": "image18-3",
          "outlineElementAuto": false,
          "transitionTimingFunction": "ease",
          "transitionRelativeZoom": 0,
          "transitionPathId": ""
        },
        "__sozi_auto__": {
          "link": false,
          "referenceElementId": "path4591",
          "outlineElementId": "image18-3",
          "outlineElementAuto": false,
          "transitionTimingFunction": "ease",
          "transitionRelativeZoom": 0,
          "transitionPathId": ""
        }
      },
      "cameraStates": {
        "layer1": {
          "cx": 563.9870266193404,
          "cy": 307.09794753696093,
          "width": 461.20742699172575,
          "height": 346.1623672521416,
          "opacity": 1,
          "angle": 0,
          "clipped": false,
          "clipXOffset": 0,
          "clipYOffset": 0,
          "clipWidthFactor": 1,
          "clipHeightFactor": 1
        },
        "__sozi_auto__": {
          "cx": 1523.9992359544794,
          "cy": 335.9581384802704,
          "width": 145.80067464679982,
          "height": 109.43168676162927,
          "opacity": 1,
          "angle": 0,
          "clipped": false,
          "clipXOffset": 0,
          "clipYOffset": 0,
          "clipWidthFactor": 1,
          "clipHeightFactor": 1
        }
      },
      "cameraOffsets": {
        "layer1": {
          "deltaX": -357.6703830486283,
          "deltaY": -325.78547531460157,
          "widthFactor": 0.2502055159430053,
          "heightFactor": 0.2734803739682748,
          "deltaAngle": 0
        }
      }
    },
    {
      "frameId": "frame4478",
      "title": "New frame",
      "timeoutMs": 0,
      "timeoutEnable": false,
      "transitionDurationMs": 2000,
      "showInFrameList": true,
      "showFrameNumber": true,
      "layerProperties": {
        "layer1": {
          "link": false,
          "referenceElementId": "path5452",
          "outlineElementId": "image18-3",
          "outlineElementAuto": false,
          "transitionTimingFunction": "ease",
          "transitionRelativeZoom": 0,
          "transitionPathId": ""
        },
        "__sozi_auto__": {
          "link": false,
          "referenceElementId": "path4591",
          "outlineElementId": "image18-3",
          "outlineElementAuto": false,
          "transitionTimingFunction": "ease",
          "transitionRelativeZoom": 0,
          "transitionPathId": ""
        }
      },
      "cameraStates": {
        "layer1": {
          "cx": 274.13054434128156,
          "cy": 750.7823488763157,
          "width": 461.5498230028556,
          "height": 346.1623672521417,
          "opacity": 1,
          "angle": 0,
          "clipped": false,
          "clipXOffset": 0,
          "clipYOffset": 0,
          "clipWidthFactor": 0.9992581602373886,
          "clipHeightFactor": 0.9999999999999999
        },
        "__sozi_auto__": {
          "cx": 1432.6786208946608,
          "cy": 475.7450017561973,
          "width": 145.90891568217233,
          "height": 109.43168676162927,
          "opacity": 1,
          "angle": 0,
          "clipped": false,
          "clipXOffset": 0,
          "clipYOffset": 0,
          "clipWidthFactor": 0.9992581602373888,
          "clipHeightFactor": 1
        }
      },
      "cameraOffsets": {
        "layer1": {
          "deltaX": 28.57816091843,
          "deltaY": 0.21521020444072292,
          "widthFactor": 2.1029867944743112,
          "heightFactor": 1.864783018085112,
          "deltaAngle": 0
        }
      }
    },
    {
      "frameId": "frame4863",
      "title": "New frame",
      "timeoutMs": 0,
      "timeoutEnable": false,
      "transitionDurationMs": 2000,
      "showInFrameList": true,
      "showFrameNumber": true,
      "layerProperties": {
        "layer1": {
          "link": false,
          "referenceElementId": "text4705-9",
          "outlineElementId": "image18-3",
          "outlineElementAuto": false,
          "transitionTimingFunction": "ease",
          "transitionRelativeZoom": 0,
          "transitionPathId": ""
        },
        "__sozi_auto__": {
          "link": false,
          "referenceElementId": "path4591",
          "outlineElementId": "image18-3",
          "outlineElementAuto": false,
          "transitionTimingFunction": "ease",
          "transitionRelativeZoom": 0,
          "transitionPathId": ""
        }
      },
      "cameraStates": {
        "layer1": {
          "cx": 257.6439689019404,
          "cy": 1075.791828734133,
          "width": 438.2725187748077,
          "height": 321.46082826804457,
          "opacity": 1,
          "angle": 0,
          "clipped": true,
          "clipXOffset": 0,
          "clipYOffset": 0,
          "clipWidthFactor": 1,
          "clipHeightFactor": 0.9981728982617474
        },
        "__sozi_auto__": {
          "cx": 1387.930609052189,
          "cy": 600.4146487260787,
          "width": 49.8789440163394,
          "height": 37.4367350233011,
          "opacity": 1,
          "angle": 0,
          "clipped": true,
          "clipXOffset": 0,
          "clipYOffset": 0,
          "clipWidthFactor": 1,
          "clipHeightFactor": 0.9999999999999999
        }
      },
      "cameraOffsets": {
        "layer1": {
          "deltaX": -5.443097748450214,
          "deltaY": -1.0055345471168948,
          "widthFactor": 2.826744787039989,
          "heightFactor": 1.7828958135894222,
          "deltaAngle": 0
        }
      }
    }
  ],
  "elementsToHide": [],
  "selectedFrames": [
    "frame6406"
  ],
  "selectedLayers": [
    "layer1",
    "__sozi_auto__"
  ],
  "editableLayers": []
}